django_db_sanitizer/__init__.py
django_db_sanitizer/admin.py
django_db_sanitizer/apps.py
django_db_sanitizer/constants.py
django_db_sanitizer/exceptions.py
django_db_sanitizer/models.py
django_db_sanitizer/registry.py
django_db_sanitizer/settings.py
django_db_sanitizer/tests.py
django_db_sanitizer/utils.py
django_db_sanitizer/views.py
django_db_sanitizer/fetchers/__init__.py
django_db_sanitizer/fetchers/base.py
django_db_sanitizer/management/__init__.py
django_db_sanitizer/management/commands/__init__.py
django_db_sanitizer/management/commands/sanitize_my_database.py
django_db_sanitizer/migrations/__init__.py
django_db_sanitizer/sanitizers/__init__.py
django_db_sanitizer/sanitizers/address.py
django_db_sanitizer/sanitizers/base.py
django_db_sanitizer/sanitizers/email.py
django_db_sanitizer/sanitizers/null.py
django_db_sanitizer/sanitizers/number.py
django_db_sanitizer/sanitizers/password.py
django_db_sanitizer/sanitizers/string.py
django_db_sanitizer/updaters/__init__.py
django_db_sanitizer/updaters/base.py
django_db_sanitizer/updaters/batch.py
django_db_sanitizer/updaters/simple.py
django_db_sanitizer/workers/__init__.py
django_db_sanitizer/workers/base.py
django_db_sanitizer-0.1.0.dist-info/DESCRIPTION.rst
django_db_sanitizer-0.1.0.dist-info/METADATA
django_db_sanitizer-0.1.0.dist-info/RECORD
django_db_sanitizer-0.1.0.dist-info/WHEEL
django_db_sanitizer-0.1.0.dist-info/metadata.json
django_db_sanitizer-0.1.0.dist-info/pbr.json
django_db_sanitizer-0.1.0.dist-info/top_level.txt
