Metadata-Version: 2.0
Name: django-db-sanitizer
Version: 0.1.0
Summary: Database data anonymizer for Django projects.
Home-page: https://github.com/resulto-admin/django-db-sanitizer
Author: Resulto Dev Team
Author-email: dev@resulto.ca
License: New BSD
Keywords: django database
Platform: UNKNOWN
Classifier: Development Status :: 4 - Beta
Classifier: Intended Audience :: Developers
Classifier: Topic :: Database
Classifier: Topic :: Software Development :: Libraries :: Python Modules
Classifier: License :: OSI Approved :: BSD License
Classifier: Framework :: Django
Classifier: Programming Language :: Python :: 2
Classifier: Programming Language :: Python :: 2.7
Classifier: Programming Language :: Python :: 3
Classifier: Programming Language :: Python :: 3.5
Requires-Dist: Django (>=1.8)
Requires-Dist: fake-factory (>=0.5.7)
Provides-Extra: test
Requires-Dist: tox (>=2.0.1); extra == 'test'
